{
  "name": "coordinate-picker",
  "displayName": "VRCoordinatePicker",
  "description": "A visual coordinate map picker that converts clicks into X/Y percentages.",
  "category": "input",
  "files": [
    "VRCoordinatePicker.tsx",
    "VRCoordinatePicker.module.css",
    "types.ts",
    "index.ts"
  ],
  "dependencies": {
    "internal": ["label", "field-error"],
    "external": ["@vora/core"]
  },
  "exports": {
    "components": ["VRCoordinatePicker"],
    "types": ["VRCoordinatePickerProps", "Coordinate"]
  }
}
